l402/__init__.py
l402/_modidx.py
l402/config.py
l402/core.py
l402/payment_providers.py
l402/utils.py
l402-0.1.0.dist-info/LICENSE
l402-0.1.0.dist-info/METADATA
l402-0.1.0.dist-info/WHEEL
l402-0.1.0.dist-info/entry_points.txt
l402-0.1.0.dist-info/top_level.txt
l402-0.1.0.dist-info/RECORD
